odoo/addons/website_img_dimension/README.rst
odoo/addons/website_img_dimension/__init__.py
odoo/addons/website_img_dimension/__manifest__.py
odoo/addons/website_img_dimension/i18n/website_img_dimension.pot
odoo/addons/website_img_dimension/readme/CONTRIBUTORS.rst
odoo/addons/website_img_dimension/readme/DESCRIPTION.rst
odoo/addons/website_img_dimension/readme/USAGE.rst
odoo/addons/website_img_dimension/static/description/icon.png
odoo/addons/website_img_dimension/static/description/index.html
odoo/addons/website_img_dimension/static/description/screenshot.png
odoo/addons/website_img_dimension/static/src/js/website_img_dimension.tooltip.js
odoo/addons/website_img_dimension/templates/assets.xml
odoo11_addon_website_img_dimension-11.0.1.0.0.99.dev10.dist-info/METADATA
odoo11_addon_website_img_dimension-11.0.1.0.0.99.dev10.dist-info/WHEEL
odoo11_addon_website_img_dimension-11.0.1.0.0.99.dev10.dist-info/top_level.txt
odoo11_addon_website_img_dimension-11.0.1.0.0.99.dev10.dist-info/RECORD
